{"200202": {"c": "HIST 316", "n": "Episodes in the History of Science II", "f": "FASS", "cr": 3.0, "ac": 49, "ca": 49, "pr": ["HIST 315"], "co": [], "i": [{"tn": "Erdal İnönü", "ta": 49, "tc": 49}], "ce": 0, "p": 26}, "200302": {"c": "HIST 316", "n": "Episodes in the History of Science II", "f": "FASS", "cr": 3.0, "ac": 56, "ca": 56, "pr": ["HIST 315"], "co": [], "i": [{"tn": "Erdal İnönü", "ta": 56, "tc": 56}], "ce": 0, "p": 29}, "200402": {"c": "HIST 316", "n": "Episodes in the History of Science II", "f": "FASS", "cr": 3.0, "ac": 32, "ca": 50, "pr": ["HIST 315"], "co": [], "i": [{"tn": "Erdal İnönü", "ta": 32, "tc": 50}], "ce": 0, "p": 61}, "200502": {"c": "HIST 316", "n": "Episodes in the History of Science II", "f": "FASS", "cr": 3.0, "ac": 55, "ca": 60, "pr": ["SPS 101", "SPS 102"], "co": [], "i": [{"tn": "Erdal İnönü", "ta": 55, "tc": 60}], "ce": 0, "p": 43}, "200902": {"c": "HIST 316", "n": "Episodes in the History of Science II", "f": "FASS", "cr": 3.0, "ac": 21, "ca": 40, "pr": ["SPS 101", "SPS 102"], "co": [], "i": [{"tn": "Harun Bekir Küçük", "ta": 21, "tc": 40}], "ce": 1, "p": 146}, "201002": {"c": "HIST 316", "n": "Episodes in the History of Science II", "f": "FASS", "cr": 3.0, "ac": 12, "ca": 40, "pr": ["SPS 101", "SPS 102"], "co": [], "i": [{"tn": "Harun Bekir Küçük", "ta": 12, "tc": 40}], "ce": 1, "p": 201}, "catList": ["A sequel to HIST 315, which pursues the story of the further development of the sciences and their impact on society from the middle of the 19th century to the present, covering, together with the West, the history of science in both Ottoman and Republican Turkey. As in HIST 315, an episodic treatment requiring extensive student participation throughout.", "A sequel to HIST 315, which pursues the story of the further development of the sciences and their  impact on society from the middle of the 19th century to the present, covering, together with the West, the history of science in both Ottoman and Republican Turkey. As in HIST 315, an episodic treatment requiring extensive student participation throughout."]}