{"201501": {"c": "GR 555S", "n": "Academic Writing for Graduate Students", "f": "FASS", "cr": 0.0, "ac": 56, "ca": 180, "pr": [], "co": [], "i": [{"tn": "Daniel Lee Calvey", "ta": 56, "tc": 180}], "ce": 0, "p": 83}, "201502": {"c": "GR 555S", "n": "Academic Writing for Graduate Students", "f": "FASS", "cr": 0.0, "ac": 88, "ca": 180, "pr": [], "co": [], "i": [{"tn": "Daniel Lee Calvey", "ta": 88, "tc": 180}], "ce": 0, "p": 53}, "201602": {"c": "GR 555S", "n": "Academic Writing for Graduate Students", "f": "FASS", "cr": 0.0, "ac": 73, "ca": 170, "pr": [], "co": [], "i": [{"tn": "Daniel Lee Calvey", "ta": 73, "tc": 170}], "ce": 0, "p": 68}, "201702": {"c": "GR 555S", "n": "Academic Writing for Graduate Students", "f": "FASS", "cr": 0.0, "ac": 83, "ca": 120, "pr": [], "co": [], "i": [{"tn": "Daniel Lee Calvey", "ta": 83, "tc": 120}], "ce": 0, "p": 64}, "201802": {"c": "GR 555S", "n": "Academic Writing for Graduate Students", "f": "FASS", "cr": 0.0, "ac": 51, "ca": 120, "pr": [], "co": [], "i": [{"tn": "Daniel Lee Calvey", "ta": 51, "tc": 120}], "ce": 0, "p": 105}, "201902": {"c": "GR 555S", "n": "Academic Writing for Graduate Students", "f": "FASS", "cr": 0.0, "ac": 80, "ca": 120, "pr": [], "co": [], "i": [{"tn": "Daniel Lee Calvey", "ta": 80, "tc": 120}], "ce": 0, "p": 70}, "catList": ["This course aims to enhance the academic communication skills of graduate students with the goal of facilitating research output. To this aim, this course helps master’s and doctoral students develop skills essential for writing academic papers and theses in English. It provides guidelines on writing for the rhetorical genres characteristic of academic writing in the social sciences and humanities such as literature review, abstract, proposal, article for publication, and thesis. Students will also help out with one or more courses offered at the University."]}