{"199901": {"c": "HIST 191", "n": "The Making of Modern Turkey I", "f": "FASS", "cr": 2.0, "ac": 53, "ca": 100, "pr": [], "co": [], "i": [{"tn": "Cemil Hüsnü Koçak", "ta": 53, "tc": 100}], "ce": 0, "p": 5}, "199902": {"c": "HIST 191", "n": "The Making of Modern Turkey I", "f": "FASS", "cr": 2.0, "ac": 92, "ca": 95, "pr": [], "co": [], "i": [{"tn": "Cemil Hüsnü Koçak", "ta": 92, "tc": 95}], "ce": 0, "p": 4}, "200001": {"c": "HIST 191", "n": "The Making of Modern Turkey I", "f": "FASS", "cr": 2.0, "ac": 206, "ca": 210, "pr": ["TLL 101"], "co": [], "i": [{"tn": "Cemil Hüsnü Koçak", "ta": 206, "tc": 210}], "ce": 0, "p": 5}, "200101": {"c": "HIST 191", "n": "The Making of Modern Turkey I", "f": "FASS", "cr": 2.0, "ac": 280, "ca": 350, "pr": ["TLL 101"], "co": [], "i": [{"tn": "Cemil Hüsnü Koçak", "ta": 280, "tc": 350}], "ce": 0, "p": 5}, "200201": {"c": "HIST 191", "n": "The Making of Modern Turkey I", "f": "FASS", "cr": 2.0, "ac": 422, "ca": 430, "pr": ["TLL 101"], "co": [], "i": [{"tn": "Cemil Hüsnü Koçak", "ta": 422, "tc": 430}], "ce": 0, "p": 2}, "200301": {"c": "HIST 191", "n": "The Making of Modern Turkey I", "f": "FASS", "cr": 2.0, "ac": 453, "ca": 460, "pr": ["TLL 101"], "co": [], "i": [{"tn": "Cemil Hüsnü Koçak", "ta": 228, "tc": 230}, {"tn": "Selçuk Akşin Somel", "ta": 225, "tc": 230}], "ce": 0, "p": 2}, "200401": {"c": "HIST 191", "n": "The Making of Modern Turkey I", "f": "FASS", "cr": 2.0, "ac": 646, "ca": 658, "pr": ["TLL 101"], "co": [], "i": [{"tn": "Cemil Hüsnü Koçak", "ta": 331, "tc": 333}, {"tn": "Selçuk Akşin Somel", "ta": 315, "tc": 325}], "ce": 0, "p": 2}, "200501": {"c": "HIST 191", "n": "Principles of Atatürk and History of Turkish Revolution I", "f": "FASS", "cr": 2.0, "ac": 575, "ca": 600, "pr": ["TLL 101"], "co": [], "i": [{"tn": "Cemil Hüsnü Koçak", "ta": 298, "tc": 300}, {"tn": "Selçuk Akşin Somel", "ta": 277, "tc": 300}], "ce": 0, "p": 4}, "200601": {"c": "HIST 191", "n": "Principles of Atatürk and History of Turkish Revolution I", "f": "FASS", "cr": 2.0, "ac": 610, "ca": 640, "pr": [], "co": [], "i": [{"tn": "Cemil Hüsnü Koçak", "ta": 317, "tc": 320}, {"tn": "Selçuk Akşin Somel", "ta": 293, "tc": 320}], "ce": 0, "p": 4}, "200701": {"c": "HIST 191", "n": "Principles of Atatürk and the History of the Turkish Revolution I", "f": "FASS", "cr": 2.0, "ac": 704, "ca": 722, "pr": ["TLL 101"], "co": [], "i": [{"tn": "Cemil Hüsnü Koçak", "ta": 360, "tc": 362}, {"tn": "Selçuk Akşin Somel", "ta": 344, "tc": 360}], "ce": 1, "p": 2}, "200801": {"c": "HIST 191", "n": "Principles of Atatürk and the History of the Turkish Revolution I", "f": "FASS", "cr": 2.0, "ac": 634, "ca": 648, "pr": ["TLL 101"], "co": [], "i": [{"tn": "Cemil Hüsnü Koçak", "ta": 329, "tc": 334}, {"tn": "Selçuk Akşin Somel", "ta": 305, "tc": 314}], "ce": 1, "p": 2}, "200802": {"c": "HIST 191", "n": "Principles of Atatürk and the History of the Turkish Revolution I", "f": "FASS", "cr": 2.0, "ac": 183, "ca": 210, "pr": ["TLL 101"], "co": [], "i": [{"tn": "Fikret Adanır", "ta": 183, "tc": 210}], "ce": 1, "p": 20}, "200901": {"c": "HIST 191", "n": "Principles of Atatürk and the History of the Turkish Revolution I", "f": "FASS", "cr": 2.0, "ac": 533, "ca": 601, "pr": ["TLL 101"], "co": [], "i": [{"tn": "Cemil Hüsnü Koçak", "ta": 297, "tc": 301}, {"tn": "Selçuk Akşin Somel", "ta": 236, "tc": 300}], "ce": 1, "p": 6}, "200902": {"c": "HIST 191", "n": "Principles of Atatürk and the History of the Turkish Revolution I", "f": "FASS", "cr": 2.0, "ac": 164, "ca": 200, "pr": ["TLL 101"], "co": [], "i": [{"tn": "Yusuf Hakan Erdem", "ta": 164, "tc": 200}], "ce": 1, "p": 22}, "201001": {"c": "HIST 191", "n": "Principles of Atatürk and the History of the Turkish Revolution I", "f": "FASS", "cr": 2.0, "ac": 448, "ca": 480, "pr": [], "co": [], "i": [{"tn": "Selçuk Akşin Somel", "ta": 235, "tc": 240}, {"tn": "Yusuf Hakan Erdem", "ta": 213, "tc": 240}], "ce": 1, "p": 3}, "201002": {"c": "HIST 191", "n": "Principles of Atatürk and the History of the Turkish Revolution I", "f": "FASS", "cr": 2.0, "ac": 211, "ca": 240, "pr": [], "co": [], "i": [{"tn": "Yusuf Hakan Erdem", "ta": 211, "tc": 240}], "ce": 1, "p": 16}, "201101": {"c": "HIST 191", "n": "Principles of Atatürk and the History of the Turkish Revolution I", "f": "FASS", "cr": 2.0, "ac": 471, "ca": 530, "pr": ["TLL 101"], "co": [], "i": [{"tn": "Selçuk Akşin Somel", "ta": 237, "tc": 265}, {"tn": "Yusuf Hakan Erdem", "ta": 234, "tc": 265}], "ce": 1, "p": 4}, "201102": {"c": "HIST 191", "n": "Principles of Atatürk and the History of the Turkish Revolution I", "f": "FASS", "cr": 2.0, "ac": 232, "ca": 250, "pr": [], "co": [], "i": [{"tn": "Fikret Adanır", "ta": 232, "tc": 250}], "ce": 1, "p": 17}, "201201": {"c": "HIST 191", "n": "Principles of Atatürk and the History of the Turkish Revolution I", "f": "FASS", "cr": 2.0, "ac": 612, "ca": 620, "pr": ["TLL 101"], "co": [], "i": [{"tn": "Selçuk Akşin Somel", "ta": 412, "tc": 420}, {"tn": "Yusuf Hakan Erdem", "ta": 200, "tc": 200}], "ce": 1, "p": 6}, "201202": {"c": "HIST 191", "n": "Principles of Atatürk and the History of the Turkish Revolution I", "f": "FASS", "cr": 2.0, "ac": 211, "ca": 250, "pr": [], "co": [], "i": [{"tn": "Fikret Adanır", "ta": 211, "tc": 250}], "ce": 1, "p": 17}, "201203": {"c": "HIST 191", "n": "Principles of Atatürk and the History of the Turkish Revolution I", "f": "FASS", "cr": 2.0, "ac": 12, "ca": 30, "pr": [], "co": [], "i": [{"tn": "Selçuk Akşin Somel", "ta": 12, "tc": 30}], "ce": 1, "p": 64}, "201301": {"c": "HIST 191", "n": "Principles of Atatürk and the History of the Turkish Revolution I", "f": "FASS", "cr": 2.0, "ac": 659, "ca": 783, "pr": [], "co": [], "i": [{"tn": "Yusuf Hakan Erdem", "ta": 348, "tc": 350}, {"tn": "Selçuk Akşin Somel", "ta": 267, "tc": 350}, {"tn": "Halil Berktay", "ta": 44, "tc": 83}], "ce": 1, "p": 6}, "201302": {"c": "HIST 191", "n": "Principles of Atatürk and the History of the Turkish Revolution I", "f": "FASS", "cr": 2.0, "ac": 237, "ca": 274, "pr": [], "co": [], "i": [{"tn": "Yusuf Hakan Erdem", "ta": 237, "tc": 274}], "ce": 1, "p": 18}, "201401": {"c": "HIST 191", "n": "Principles of Atatürk and the History of the Turkish Revolution I", "f": "FASS", "cr": 2.0, "ac": 619, "ca": 658, "pr": [], "co": [], "i": [{"tn": "Yusuf Hakan Erdem", "ta": 294, "tc": 295}, {"tn": "Selçuk Akşin Somel", "ta": 276, "tc": 293}, {"tn": "Adam Bennett McConnel", "ta": 49, "tc": 70}], "ce": 1, "p": 5}, "201402": {"c": "HIST 191", "n": "Principles of Atatürk and the History of the Turkish Revolution I", "f": "FASS", "cr": 2.0, "ac": 251, "ca": 294, "pr": [], "co": [], "i": [{"tn": "Yusuf Hakan Erdem", "ta": 238, "tc": 279}, {"tn": "Adam Bennett McConnel", "ta": 13, "tc": 15}], "ce": 1, "p": 19}, "201403": {"c": "HIST 191", "n": "Principles of Atatürk and the History of the Turkish Revolution I", "f": "FASS", "cr": 2.0, "ac": 8, "ca": 50, "pr": [], "co": [], "i": [{"tn": "Adam Bennett McConnel", "ta": 8, "tc": 50}], "ce": 1, "p": 80}, "201501": {"c": "HIST 191", "n": "Principles of Atatürk and the History of the Turkish Revolution I", "f": "FASS", "cr": 2.0, "ac": 732, "ca": 800, "pr": [], "co": [], "i": [{"tn": "Yusuf Hakan Erdem", "ta": 363, "tc": 365}, {"tn": "Selçuk Akşin Somel", "ta": 285, "tc": 350}, {"tn": "Adam Bennett McConnel", "ta": 84, "tc": 85}], "ce": 1, "p": 7}, "201502": {"c": "HIST 191", "n": "Principles of Atatürk and the History of the Turkish Revolution I", "f": "FASS", "cr": 2.0, "ac": 280, "ca": 314, "pr": [], "co": [], "i": [{"tn": "Halil Berktay", "ta": 258, "tc": 280}, {"tn": "Adam Bennett McConnel", "ta": 22, "tc": 34}], "ce": 1, "p": 17}, "201503": {"c": "HIST 191", "n": "Principles of Atatürk and the History of the Turkish Revolution I", "f": "FASS", "cr": 2.0, "ac": 18, "ca": 25, "pr": [], "co": [], "i": [{"tn": "Adam Bennett McConnel", "ta": 18, "tc": 25}], "ce": 1, "p": 68}, "201601": {"c": "HIST 191", "n": "Principles of Atatürk and the History of the Turkish Revolution I", "f": "FASS", "cr": 2.0, "ac": 748, "ca": 860, "pr": [], "co": [], "i": [{"tn": "Cemil Hüsnü Koçak", "ta": 370, "tc": 380}, {"tn": "Selçuk Akşin Somel", "ta": 323, "tc": 380}, {"tn": "Adam Bennett McConnel", "ta": 55, "tc": 100}], "ce": 1, "p": 2}, "201602": {"c": "HIST 191", "n": "Principles of Atatürk and the History of the Turkish Revolution I", "f": "FASS", "cr": 2.0, "ac": 305, "ca": 330, "pr": [], "co": [], "i": [{"tn": "Yusuf Hakan Erdem", "ta": 283, "tc": 300}, {"tn": "Adam Bennett McConnel", "ta": 22, "tc": 30}], "ce": 1, "p": 18}, "201701": {"c": "HIST 191", "n": "Principles of Atatürk and the History of the Turkish Revolution I", "f": "FASS", "cr": 2.0, "ac": 605, "ca": 680, "pr": [], "co": [], "i": [{"tn": "Yusuf Hakan Erdem", "ta": 283, "tc": 295}, {"tn": "Selçuk Akşin Somel", "ta": 262, "tc": 285}, {"tn": "Adam Bennett McConnel", "ta": 60, "tc": 100}], "ce": 1, "p": 4}, "201702": {"c": "HIST 191", "n": "Principles of Atatürk and the History of the Turkish Revolution I", "f": "FASS", "cr": 2.0, "ac": 259, "ca": 330, "pr": [], "co": [], "i": [{"tn": "Yusuf Hakan Erdem", "ta": 241, "tc": 300}, {"tn": "Adam Bennett McConnel", "ta": 18, "tc": 30}], "ce": 1, "p": 20}, "201801": {"c": "HIST 191", "n": "Principles of Atatürk and the History of the Turkish Revolution I", "f": "FASS", "cr": 2.0, "ac": 590, "ca": 698, "pr": [], "co": [], "i": [{"tn": "Yusuf Hakan Erdem", "ta": 287, "tc": 298}, {"tn": "Cemil Hüsnü Koçak", "ta": 245, "tc": 300}, {"tn": "Adam Bennett McConnel", "ta": 58, "tc": 100}], "ce": 1, "p": 6}, "201802": {"c": "HIST 191", "n": "Principles of Atatürk and the History of the Turkish Revolution I", "f": "FASS", "cr": 2.0, "ac": 243, "ca": 330, "pr": [], "co": [], "i": [{"tn": "Yusuf Hakan Erdem", "ta": 232, "tc": 300}, {"tn": "Adam Bennett McConnel", "ta": 11, "tc": 30}], "ce": 1, "p": 24}, "201901": {"c": "HIST 191", "n": "Principles of Atatürk and the History of the Turkish Revolution I", "f": "FASS", "cr": 2.0, "ac": 702, "ca": 815, "pr": [], "co": [], "i": [{"tn": "Selçuk Akşin Somel", "ta": 603, "tc": 700}, {"tn": "Adam Bennett McConnel", "ta": 99, "tc": 115}], "ce": 1, "p": 6}, "201902": {"c": "HIST 191", "n": "Principles of Atatürk and the History of the Turkish Revolution I", "f": "FASS", "cr": 2.0, "ac": 332, "ca": 380, "pr": [], "co": [], "i": [{"tn": "Cemil Hüsnü Koçak", "ta": 314, "tc": 350}, {"tn": "Adam Bennett McConnel", "ta": 18, "tc": 30}], "ce": 1, "p": 15}, "202001": {"c": "HIST 191", "n": "Principles of Atatürk and the History of the Turkish Revolution I", "f": "FASS", "cr": 2.0, "ac": 650, "ca": 770, "pr": [], "co": [], "i": [{"tn": "Yusuf Hakan Erdem", "ta": 303, "tc": 320}, {"tn": "Selçuk Akşin Somel", "ta": 264, "tc": 320}, {"tn": "Adam Bennett McConnel", "ta": 83, "tc": 130}], "ce": 1, "p": 6}, "catList": ["This basic ,comprehensive  survey of the politics, economics and sociology of Turkish modernization  begins with a review of the pressures building up on the Ottoman Empire ,and the recurring confrontations  between  the conservative and  the reform -minded wings of the ruling elite ,through the 17th and 18th centuries ,dovetailing into the challenges confronting the porte under Selim 3 and Mahmud 2. The long drawn -out tragedy of the Turkish 19th century,comprising: a context of continuing  retreat and territorial contraction ,as well as of deepening despair ,summed up as a non -colonial pattern of incorporation ;the complicated relationships between the Great powers and the various Balkan nationalisims;the initial introduction and the subsequent  expansion of modernization agendas  from the top down;the interplay of political and economics factors, and of local vs.İnternational forces ,in the major crises of the 1830s,the 1850s ,and the 1870s;the course of restructuring in the legal ,administrative educational, fiscal and economic spheres;the ancient regime complexity set up by Tanzimat dualisms;the Ottomans' ambition to modernize and to be recognized as modern (and hence of being admitted into the Concert of Europe);the gradual emergence of a state of law,and the replacement of the First Constitution's abortive liberalism by the resurgent  authoritarianism of the Hamidian era.", "This basic, comprehensive survey of the politics, economics and sociology of Turkish modernization begins with a review of the pressures building up on the Ottoman Empire, and the recurring confrontations between the conservative and the reform-minded wings of the ruling elite, through the 17th and 18th centuries, dovetailing into the challenges confronting the porte under Selim III and Mahmud II. The long drawn-out tragedy of the Turkish 19th century, comprising: a context of continuing retreat and territorial contraction, as well as of deepening despair, summed up as a non-colonial pattern of incorporation; the complicated relationships between the Great Powers and the various Balkan nationalisms; the initial introduction and the subsequent expansion of modernization agendas from the top down; the interplay of political and economic factors, and of local vs international forces, in the major crises of the 1830s, the 1850s, and the 1870s; the course of restructuring in the legal, administrative, educational, fiscal and economic spheres; the ancien régime complexity set up by Tanzimat dualisms; the Ottomans' ambition to modernize and to be recognized as modern (and hence of being admitted into the Concert of Europe); the gradual emergence of a state of law, and the replacement of the First Constitution's abortive liberalism by the resurgent authoritarianism of the Hamidian era."]}