{"200302": {"c": "GSM 5216", "n": "E-business and CRM", "f": "SOM", "cr": 2.0, "ac": 2, "ca": 13, "pr": [], "co": [], "i": [{"tn": "Mustafa Orhan", "ta": 2, "tc": 13}], "ce": 0, "p": 271}, "catList": ["Objective of the course is to have participants got basic concepts of e-Business transformation from different perspectives such as project methodology, change management, technology selection criteria, security, cost control and decision support processes. The course aims to introduce practical knowledge as well as concepts and theory In order to get the participants visualize the practice and gain familiarity with real business environment, the course is composed of short seminars that will be held by outstanding executives from IT industry and/or other businesses. There are 14 nominated guest speakers&finalized speaker list and the seminar agenda will be announced later. Basic e-Business topics will be covered in the first 3 weeks in order to get participants become familiar with the core concept. Following weeks, each topic will be supported by business cases and ad-hoc seminars given by outstanding executives. Videos and other online / audio-visual materials will be utilized as needed."]}