{"200602": {"c": "CULT 590", "n": "Pro-thesis Seminar", "f": "FASS", "cr": 0.0, "ac": 12, "ca": 15, "pr": [], "co": [], "i": [{"tn": "Leyla Neyzi", "ta": 12, "tc": 15}], "ce": 0, "p": 190}, "200701": {"c": "CULT 590", "n": "Pro-thesis Seminar", "f": "FASS", "cr": 0.0, "ac": 10, "ca": 25, "pr": [], "co": [], "i": [{"tn": "Leyla Neyzi", "ta": 10, "tc": 25}], "ce": 0, "p": 227}, "200801": {"c": "CULT 590", "n": "Pro-thesis Seminar", "f": "FASS", "cr": 0.0, "ac": 1, "ca": 20, "pr": [], "co": [], "i": [{"tn": "Ayşe Parla", "ta": 1, "tc": 20}], "ce": 0, "p": 411}, "200802": {"c": "CULT 590", "n": "Pro-thesis Seminar", "f": "FASS", "cr": 0.0, "ac": 2, "ca": 12, "pr": [], "co": [], "i": [{"tn": "Ayşe Parla", "ta": 2, "tc": 12}], "ce": 0, "p": 387}, "200901": {"c": "CULT 590", "n": "Pro-thesis Seminar", "f": "FASS", "cr": 0.0, "ac": 8, "ca": 20, "pr": [], "co": [], "i": [{"tn": "Hülya Adak", "ta": 8, "tc": 20}], "ce": 0, "p": 296}, "200902": {"c": "CULT 590", "n": "Pro-thesis Seminar", "f": "FASS", "cr": 0.0, "ac": 3, "ca": 12, "pr": [], "co": [], "i": [{"tn": "Hülya Adak", "ta": 3, "tc": 12}], "ce": 0, "p": 397}, "201001": {"c": "CULT 590", "n": "Pro-thesis Seminar", "f": "FASS", "cr": 0.0, "ac": 10, "ca": 20, "pr": [], "co": [], "i": [{"tn": "Hülya Adak", "ta": 10, "tc": 20}], "ce": 0, "p": 287}, "201002": {"c": "CULT 590", "n": "Pro-thesis Seminar", "f": "FASS", "cr": 0.0, "ac": 4, "ca": 25, "pr": [], "co": [], "i": [{"tn": "Hülya Adak", "ta": 4, "tc": 25}], "ce": 0, "p": 361}, "201101": {"c": "CULT 590", "n": "Pro-thesis Seminar", "f": "FASS", "cr": 0.0, "ac": 27, "ca": 30, "pr": [], "co": [], "i": [{"tn": "Annedith Schneider", "ta": 27, "tc": 30}], "ce": 0, "p": 113}, "201102": {"c": "CULT 590", "n": "Pro-thesis Seminar", "f": "FASS", "cr": 0.0, "ac": 9, "ca": 30, "pr": [], "co": [], "i": [{"tn": "Annedith Schneider", "ta": 9, "tc": 30}], "ce": 0, "p": 257}, "201201": {"c": "CULT 590", "n": "Pro-thesis Seminar", "f": "FASS", "cr": 0.0, "ac": 11, "ca": 27, "pr": [], "co": [], "i": [{"tn": "Annedith Schneider", "ta": 11, "tc": 27}], "ce": 0, "p": 286}, "201202": {"c": "CULT 590", "n": "Pro-thesis Seminar", "f": "FASS", "cr": 0.0, "ac": 11, "ca": 30, "pr": [], "co": [], "i": [{"tn": "Annedith Schneider", "ta": 11, "tc": 30}], "ce": 0, "p": 236}, "201301": {"c": "CULT 590", "n": "Pro-thesis Seminar", "f": "FASS", "cr": 0.0, "ac": 15, "ca": 20, "pr": [], "co": [], "i": [{"tn": "Annedith Schneider", "ta": 15, "tc": 20}], "ce": 0, "p": 218}, "201302": {"c": "CULT 590", "n": "Pro-thesis Seminar", "f": "FASS", "cr": 0.0, "ac": 14, "ca": 30, "pr": [], "co": [], "i": [{"tn": "Annedith Schneider", "ta": 14, "tc": 30}], "ce": 0, "p": 204}, "201401": {"c": "CULT 590", "n": "Pro-thesis Seminar", "f": "FASS", "cr": 0.0, "ac": 10, "ca": 20, "pr": [], "co": [], "i": [{"tn": "Faik Kurtulmuş", "ta": 10, "tc": 20}], "ce": 0, "p": 297}, "201402": {"c": "CULT 590", "n": "Pro-thesis Seminar", "f": "FASS", "cr": 0.0, "ac": 8, "ca": 30, "pr": [], "co": [], "i": [{"tn": "Faik Kurtulmuş", "ta": 8, "tc": 30}], "ce": 0, "p": 296}, "201501": {"c": "CULT 590", "n": "Pro-thesis Seminar", "f": "FASS", "cr": 0.0, "ac": 18, "ca": 20, "pr": [], "co": [], "i": [{"tn": "Ayşe Gül Altınay", "ta": 18, "tc": 20}], "ce": 0, "p": 238}, "201601": {"c": "CULT 590", "n": "Pro-thesis Seminar", "f": "FASS", "cr": 0.0, "ac": 3, "ca": 20, "pr": [], "co": [], "i": [{"tn": "Faik Kurtulmuş", "ta": 3, "tc": 20}], "ce": 0, "p": 429}, "201602": {"c": "CULT 590", "n": "Pro-thesis Seminar", "f": "FASS", "cr": 0.0, "ac": 8, "ca": 30, "pr": [], "co": [], "i": [{"tn": "Faik Kurtulmuş", "ta": 8, "tc": 30}], "ce": 0, "p": 337}, "201701": {"c": "CULT 590", "n": "Pro-thesis Seminar", "f": "FASS", "cr": 0.0, "ac": 14, "ca": 20, "pr": [], "co": [], "i": [{"tn": "Faik Kurtulmuş", "ta": 14, "tc": 20}], "ce": 0, "p": 258}, "201702": {"c": "CULT 590", "n": "Pro-thesis Seminar", "f": "FASS", "cr": 0.0, "ac": 1, "ca": 20, "pr": [], "co": [], "i": [{"tn": "Faik Kurtulmuş", "ta": 1, "tc": 20}], "ce": 0, "p": 499}, "201801": {"c": "CULT 590", "n": "Pro-thesis Seminar", "f": "FASS", "cr": 0.0, "ac": 1, "ca": 20, "pr": [], "co": [], "i": [{"tn": "Cenk Özbay", "ta": 1, "tc": 20}], "ce": 0, "p": 484}, "201802": {"c": "CULT 590", "n": "Pro-thesis Seminar", "f": "FASS", "cr": 0.0, "ac": 7, "ca": 20, "pr": [], "co": [], "i": [{"tn": "Cenk Özbay", "ta": 7, "tc": 20}], "ce": 0, "p": 373}, "201901": {"c": "CULT 590", "n": "Pro-thesis Seminar", "f": "FASS", "cr": 0.0, "ac": 1, "ca": 20, "pr": [], "co": [], "i": [{"tn": "Cenk Özbay", "ta": 1, "tc": 20}], "ce": 0, "p": 492}, "201902": {"c": "CULT 590", "n": "Pro-thesis Seminar", "f": "FASS", "cr": 0.0, "ac": 12, "ca": 20, "pr": [], "co": [], "i": [{"tn": "Cenk Özbay", "ta": 12, "tc": 20}], "ce": 0, "p": 310}, "202001": {"c": "CULT 590", "n": "Pro-thesis Seminar", "f": "FASS", "cr": 0.0, "ac": 7, "ca": 20, "pr": [], "co": [], "i": [{"tn": "Cenk Özbay", "ta": 7, "tc": 20}], "ce": 0, "p": 401}, "catList": ["Pro-Thesis Seminar provides a non-credit framework for the continuous monitoring and collegial discussion of MA students' thesis research and writing, which they are expected to accomplish under the supervision of a Faculty member from the relevant field."]}