{"200402": {"c": "MGMT 902", "n": "Turkish Business Context", "f": "SOM", "cr": 1.5, "ac": 23, "ca": 24, "pr": [], "co": [], "i": [{"tn": "Behlül Üsdiken", "ta": 23, "tc": 24}], "ce": 0, "p": 77}, "200502": {"c": "MGMT 902", "n": "Turkish Business Context", "f": "SOM", "cr": 1.5, "ac": 26, "ca": 26, "pr": [], "co": [], "i": [{"tn": "Behlül Üsdiken", "ta": 26, "tc": 26}], "ce": 0, "p": 85}, "200602": {"c": "MGMT 902", "n": "Turkish Business Context", "f": "SOM", "cr": 1.5, "ac": 38, "ca": 39, "pr": [], "co": [], "i": [{"tn": "Fazıl Ahmet Öncü", "ta": 38, "tc": 39}], "ce": 0, "p": 69}, "catList": ["Using institutional and cultural perspectives, this course helps students to develop a better understanding of the Turkish business environment. Topics include forms of business organization in Turkey, managerial behaviors and practices, and management education and managerial careers. Coverage of these topics is located within the context of the Turkish industrialization process."]}