{"200602": {"c": "FIN 451", "n": "Selected Topics in Finance II", "f": "FASS", "cr": 3.0, "ac": 13, "ca": 30, "pr": ["FIN 301"], "co": [], "i": [{"tn": "Abdullah Yavaş", "ta": 13, "tc": 30}], "ce": 0, "p": 185}, "200802": {"c": "FIN 451", "n": "Selected Topics in Finance II", "f": "FASS", "cr": 3.0, "ac": 8, "ca": 30, "pr": ["FIN 301"], "co": [], "i": [{"tn": "Köksal Çoban", "ta": 8, "tc": 30}], "ce": 0, "p": 257}, "201002": {"c": "FIN 451", "n": "Selected Topics in Finance II", "f": "FASS", "cr": 3.0, "ac": 10, "ca": 20, "pr": ["FIN 301"], "co": [], "i": [{"tn": "Köksal Çoban", "ta": 10, "tc": 20}], "ce": 0, "p": 227}, "201102": {"c": "FIN 451", "n": "Selected Topics in Finance II", "f": "SOM", "cr": 3.0, "ac": 7, "ca": 20, "pr": ["FIN 301"], "co": [], "i": [{"tn": "Köksal Çoban", "ta": 7, "tc": 20}], "ce": 0, "p": 295}, "201202": {"c": "FIN 451", "n": "Selected Topics in Finance II", "f": "SOM", "cr": 3.0, "ac": 8, "ca": 20, "pr": ["FIN 301"], "co": [], "i": [{"tn": "Köksal Çoban", "ta": 8, "tc": 20}], "ce": 0, "p": 287}, "201302": {"c": "FIN 451", "n": "Selected Topics in Finance II", "f": "SOM", "cr": 3.0, "ac": 7, "ca": 20, "pr": ["FIN 301"], "co": [], "i": [{"tn": "Köksal Çoban", "ta": 7, "tc": 20}], "ce": 0, "p": 311}, "catList": ["Topics of these courses will be announced when they are offered."]}