{"200803": {"c": "MS 413", "n": "Information Systems", "f": "FENS", "cr": 3.0, "ac": 56, "ca": 70, "pr": [], "co": [], "i": [{"tn": "Haluk Demirkan", "ta": 56, "tc": 70}], "ce": 0, "p": 9}, "200903": {"c": "MS 413", "n": "Information Systems", "f": "FENS", "cr": 3.0, "ac": 72, "ca": 80, "pr": [], "co": [], "i": [{"tn": "Haluk Demirkan", "ta": 72, "tc": 80}], "ce": 0, "p": 6}, "201003": {"c": "MS 413", "n": "Information Systems", "f": "FENS", "cr": 3.0, "ac": 55, "ca": 87, "pr": [], "co": [], "i": [{"tn": "Haluk Demirkan", "ta": 55, "tc": 87}], "ce": 0, "p": 10}, "201103": {"c": "MS 413", "n": "Information Systems", "f": "FENS", "cr": 3.0, "ac": 43, "ca": 45, "pr": [], "co": [], "i": [{"tn": "Haluk Demirkan", "ta": 43, "tc": 45}], "ce": 0, "p": 15}, "201203": {"c": "MS 413", "n": "Information Systems", "f": "FENS", "cr": 3.0, "ac": 17, "ca": 40, "pr": [], "co": [], "i": [{"tn": "Haluk Demirkan", "ta": 17, "tc": 40}], "ce": 0, "p": 48}, "201401": {"c": "MS 413", "n": "Information Systems", "f": "FENS", "cr": 3.0, "ac": 46, "ca": 70, "pr": [], "co": [], "i": [{"tn": "Ahmet Onur Durahim", "ta": 46, "tc": 70}], "ce": 0, "p": 92}, "201402": {"c": "MS 413", "n": "Information Systems", "f": "FENS", "cr": 3.0, "ac": 50, "ca": 65, "pr": [], "co": [], "i": [{"tn": "Ahmet Onur Durahim", "ta": 50, "tc": 65}], "ce": 0, "p": 77}, "catList": ["Introduction to the principles and practices in the design and use of computer-based information in today's enterprises; software and hardware used in information systems; language types; database management and security requirements; management of information systems and computer technology; applications in different industries and future directions."]}