{"200002": {"c": "MAT 504", "n": "Computer Modeling in Materials Science", "f": "FENS", "cr": 3.0, "ac": 3, "ca": 25, "pr": [], "co": [], "i": [{"tn": "Canan At覺lgan", "ta": 3, "tc": 25}], "ce": 0, "p": 87}, "200301": {"c": "MAT 504", "n": "Computer Modeling in Materials Science", "f": "FENS", "cr": 3.0, "ac": 8, "ca": 10, "pr": [], "co": [], "i": [{"tn": "Canan At覺lgan", "ta": 8, "tc": 10}], "ce": 0, "p": 181}, "201002": {"c": "MAT 504", "n": "Computer Modeling in Materials Science", "f": "FENS", "cr": 3.0, "ac": 7, "ca": 15, "pr": [], "co": [], "i": [{"tn": "Canan At覺lgan", "ta": 7, "tc": 15}], "ce": 0, "p": 287}, "201502": {"c": "MAT 504", "n": "Computer Modeling in Materials Science", "f": "FENS", "cr": 3.0, "ac": 6, "ca": 30, "pr": [], "co": [], "i": [{"tn": "Canan At覺lgan", "ta": 6, "tc": 30}], "ce": 0, "p": 346}, "catList": ["Model systems and interaction potentials. Short review of statistical mechanics. Monte Carlo methods, molecular and stochastic dynamics, quantum simulations. Advanced simulation techniques; e.g. free energy estimation, non-equilibrium molecular dynamics. Applications to polymers, surfaces, gels, biomolecules."]}