{"201402": {"c": "BP 512", "n": "International Marketing Strategy", "f": "FASS", "cr": 1.5, "ac": 30, "ca": 40, "pr": [], "co": [], "i": [{"tn": "Attila Yaprak", "ta": 30, "tc": 40}], "ce": 0, "p": 116}, "201501": {"c": "BP 512", "n": "International Marketing I", "f": "FASS", "cr": 1.5, "ac": 33, "ca": 50, "pr": [], "co": [], "i": [{"tn": "Attila Yaprak", "ta": 33, "tc": 50}], "ce": 0, "p": 132}, "201601": {"c": "BP 512", "n": "International Marketing I", "f": "FASS", "cr": 1.5, "ac": 27, "ca": 50, "pr": [], "co": [], "i": [{"tn": "Attila Yaprak", "ta": 27, "tc": 50}], "ce": 0, "p": 182}, "201701": {"c": "BP 512", "n": "International Marketing I", "f": "SOM", "cr": 1.5, "ac": 23, "ca": 25, "pr": [], "co": [], "i": [{"tn": "Attila Yaprak", "ta": 23, "tc": 25}], "ce": 0, "p": 188}, "catList": ["International Marketing Strategy is a problem-solving-oriented marketing course designed for marketing executives and second-year MBA students who expect to undertake marketing assignments as part of their career paths to general management, and students planning functional careers in multinational, global, and internationalizing enterprises. My objective in this course is to present a systematic application of strategic marketing in the global environment. I present an integrated treatment of conceptual and managerial issues in contemporary international marketing based on the state-of-the-art research in the field. The focus is on the formulation of comprehensive marketing strategies by multinationals from developed economies, such as the United States, but also from emerging economies, such as India, China, S. Africa, and Turkey, competing in global industries. The course is designed to provide an appreciation for cross-functional and interdisciplinary perspectives in international business. This is because today’s global operations increasingly require these proficiencies in managing core business processes."]}