{"200402": {"c": "ORG 612", "n": "Organizational Behaviour and HR Management", "f": "SOM", "cr": 3.0, "ac": 1, "ca": 5, "pr": [], "co": [], "i": [{"tn": "Arzu Syeda Wasti", "ta": 1, "tc": 5}], "ce": 0, "p": 304}, "200502": {"c": "ORG 612", "n": "Organizational Behaviour and HR Management", "f": "SOM", "cr": 3.0, "ac": 3, "ca": 6, "pr": [], "co": [], "i": [{"tn": "Arzu Syeda Wasti", "ta": 3, "tc": 6}], "ce": 0, "p": 308}, "200901": {"c": "ORG 612", "n": "Organizational Behavior", "f": "SOM", "cr": 3.0, "ac": 6, "ca": 10, "pr": [], "co": [], "i": [{"tn": "Arzu Syeda Wasti", "ta": 6, "tc": 10}], "ce": 1, "p": 342}, "201102": {"c": "ORG 612", "n": "Organizational Behavior", "f": "SOM", "cr": 3.0, "ac": 6, "ca": 16, "pr": [], "co": [], "i": [{"tn": "Arzu Syeda Wasti", "ta": 6, "tc": 16}], "ce": 1, "p": 310}, "201201": {"c": "ORG 612", "n": "Organizational Behavior", "f": "SOM", "cr": 3.0, "ac": 0, "ca": 1, "pr": [], "co": [], "i": [{"tn": "Arzu Syeda Wasti", "ta": 0, "tc": 1}], "ce": 1, "p": 505}, "201401": {"c": "ORG 612", "n": "Organizational Behavior", "f": "SOM", "cr": 3.0, "ac": 3, "ca": 5, "pr": [], "co": [], "i": [{"tn": "Mahmut Bayaz覺t", "ta": 3, "tc": 5}], "ce": 1, "p": 418}, "201501": {"c": "ORG 612", "n": "Organizational Behavior", "f": "SOM", "cr": 3.0, "ac": 2, "ca": 5, "pr": [], "co": [], "i": [{"tn": "Mahmut Bayaz覺t", "ta": 2, "tc": 5}], "ce": 1, "p": 444}, "201701": {"c": "ORG 612", "n": "Organizational Behavior", "f": "SOM", "cr": 3.0, "ac": 2, "ca": 20, "pr": [], "co": [], "i": [{"tn": "Mahmut Bayaz覺t", "ta": 2, "tc": 20}], "ce": 1, "p": 443}, "202001": {"c": "ORG 612", "n": "Organizational Behavior", "f": "SOM", "cr": 3.0, "ac": 4, "ca": 15, "pr": [], "co": [], "i": [{"tn": "Mahmut Bayaz覺t", "ta": 4, "tc": 15}], "ce": 1, "p": 449}, "catList": ["This seminar is designed to provide students with a broad overview of the major topics in the fields of organizational behavior (OB) and human resources management (HRM). The course starts off with a critical introduction to the field of OB, followed by an orientation to research on foundations of individual behavior and group processes. The course then proceeds to cover other OB topics like intergroup relations, leadership, and organizational culture The second half of the seminar is a touring of the major areas of human resources management namely staffing, socialization, training, performance appraisal and compensation including a discussion on employee withdrawal behaviors such as absenteeism and turnover. Finally, the important issue of HRM and organizational effectiveness and future directions of both fields are covered.", "This seminar is designed to provide students with a broad overview of the major topics in the field of organizational behavior (OB). The course starts off with a critical introduction to the field of OB, followed by an orientation to research on individual differences, job attitudes such as job satisfaction and organizational commitment, motivation theories, psychological contracts and interorganizational trust. The course then proceeds to cover other OB topics like group dynamics, leadership, and organizational culture, and the literature on the relationship between these variables and processes and various job outcomes such as citizenship behaviors, and various job outcomes such as citizenship behaviors,"]}