{"200201": {"c": "IE 592", "n": "Project Course", "f": "FENS", "cr": 0.0, "ac": 3, "ca": 10, "pr": [], "co": [], "i": [{"tn": "Gürdal Ertek", "ta": 3, "tc": 10}], "ce": 0, "p": 197}, "200301": {"c": "IE 592", "n": "Project Course", "f": "FENS", "cr": 0.0, "ac": 5, "ca": 10, "pr": [], "co": [], "i": [{"tn": "Tonguç Ünlüyurt", "ta": 5, "tc": 10}], "ce": 0, "p": 213}, "200401": {"c": "IE 592", "n": "Project Course", "f": "FENS", "cr": 0.0, "ac": 5, "ca": 15, "pr": [], "co": [], "i": [{"tn": "Tonguç Ünlüyurt", "ta": 5, "tc": 15}], "ce": 0, "p": 244}, "200501": {"c": "IE 592", "n": "Project Course", "f": "FENS", "cr": 0.0, "ac": 2, "ca": 15, "pr": [], "co": [], "i": [{"tn": "Tonguç Ünlüyurt", "ta": 2, "tc": 15}], "ce": 0, "p": 323}, "200701": {"c": "IE 592", "n": "Project Course", "f": "FENS", "cr": 0.0, "ac": 2, "ca": 50, "pr": [], "co": [], "i": [{"tn": "Kerem Bülbül", "ta": 2, "tc": 50}], "ce": 0, "p": 376}, "200801": {"c": "IE 592", "n": "Project Course", "f": "FENS", "cr": 0.0, "ac": 2, "ca": 7, "pr": [], "co": [], "i": [{"tn": "Bülent Çatay", "ta": 2, "tc": 7}], "ce": 0, "p": 392}, "200901": {"c": "IE 592", "n": "Project Course", "f": "FENS", "cr": 0.0, "ac": 2, "ca": 2, "pr": [], "co": [], "i": [{"tn": "Bülent Çatay", "ta": 2, "tc": 2}], "ce": 0, "p": 429}, "201001": {"c": "IE 592", "n": "Project Course", "f": "FENS", "cr": 0.0, "ac": 1, "ca": 1, "pr": [], "co": [], "i": [{"tn": "Bülent Çatay", "ta": 1, "tc": 1}], "ce": 0, "p": 459}, "catList": ["All graduate students pursuing a non-thesis M.Sc. Program are required to complete a project. The project topic and contents are based on the interest and background of the student and are approved by the faculty member serving as the project supervisor. At the completion of the project, the student is required to submit a final report. The final report is to be approved by the project supervisor."]}